numcodecs_bitmap_index/__init__.py
numcodecs_bitmap_index/py.typed
numcodecs_bitmap_index/typing.py
numcodecs_bitmap_index-0.1.2.dist-info/METADATA
numcodecs_bitmap_index-0.1.2.dist-info/WHEEL
numcodecs_bitmap_index-0.1.2.dist-info/entry_points.txt
numcodecs_bitmap_index-0.1.2.dist-info/licenses/LICENSE
numcodecs_bitmap_index-0.1.2.dist-info/RECORD
